rift_tonlib/__init__.py
rift_tonlib/client.py
rift_tonlib/tonlibjson.py
rift_tonlib/distlib/darwin/libtonlibjson.arm64.dylib
rift_tonlib/distlib/darwin/libtonlibjson.x86_64.dylib
rift_tonlib/distlib/freebsd/libtonlibjson.amd64.so
rift_tonlib/distlib/linux/libtonlibjson.aarch64.so
rift_tonlib/distlib/linux/libtonlibjson.x86_64.so
rift_tonlib/distlib/windows/tonlibjson.amd64.dll
rift_tonlib/types/__init__.py
rift_tonlib/types/cell.py
rift_tonlib/types/dict_utils.py
rift_tonlib/types/stack_utils.py
rift_tonlib/utils/__init__.py
rift_tonlib/utils/address.py
rift_tonlib/utils/common.py
rift_tonlib/utils/tlb.py
rift_tonlib/utils/tokens.py
rift_tonlib/utils/wallet.py
rift_tonlib-0.0.3.dist-info/LICENSE
rift_tonlib-0.0.3.dist-info/METADATA
rift_tonlib-0.0.3.dist-info/WHEEL
rift_tonlib-0.0.3.dist-info/top_level.txt
rift_tonlib-0.0.3.dist-info/zip-safe
rift_tonlib-0.0.3.dist-info/RECORD
