Metadata-Version: 2.1
Name: rift-tonlib
Version: 0.0.3
Summary: Python API for TON (Telegram Open Network)
Home-page: https://github.com/AminRezaei0x443/pytonlib
Author: Amin Rezaei
Author-email: AminRezaei0x443@gmail.com
Requires-Python: >=3.7
License-File: LICENSE
Requires-Dist: bitarray
Requires-Dist: crcset (>=0.0.4)
Requires-Dist: requests (>=2.27.1)
